mosquito_remover
