Metadata-Version: 2.1
Name: mosquito-remover
Version: 1.0.0
Summary: This is only for entertainment purposes (I made this for fun!)
Home-page: UNKNOWN
Author: Arib Muhtasim
Author-email: aribmuhtasim22@gmail.com
License: MIT
Platform: UNKNOWN
Classifier: Development Status :: 5 - Production/Stable
Classifier: Intended Audience :: Education
Classifier: Operating System :: Microsoft :: Windows :: Windows 10
Classifier: License :: OSI Approved :: MIT License
Classifier: Programming Language :: Python :: 3
